{
  "started": "20260408",
  "total_days": 2,
  "total_picks": 25,
  "wins": 16,
  "losses": 9,
  "voids": 114,
  "total_staked": 553,
  "profit_units": 0.48,
  "pro_picks": 25,
  "pro_wins": 16,
  "pro_losses": 9,
  "pro_staked": 421,
  "pro_profit": 0.48,
  "daily": [
    {
      "date": "20260408",
      "picks": 10,
      "wins": 8,
      "losses": 2,
      "accuracy": 80.0,
      "staked": 105,
      "profit": 4.52,
      "pro_wins": 8,
      "pro_losses": 2,
      "pro_profit": 4.52
    },
    {
      "date": "20260409",
      "picks": 15,
      "wins": 8,
      "losses": 7,
      "accuracy": 53.3,
      "staked": 448,
      "profit": -4.04,
      "pro_wins": 8,
      "pro_losses": 7,
      "pro_profit": -4.04,
      "top5_wins": 1,
      "top5_losses": 2,
      "top5_profit": -11.6,
      "top5_roi_pct": -31.4
    }
  ],
  "accuracy": 64.0,
  "roi_pct": 0.1,
  "pro_accuracy": 64.0,
  "pro_roi_pct": 0.1,
  "last_updated": "2026-04-10T07:49:57.155121+00:00",
  "top5_days": 1,
  "top5_picks": 5,
  "top5_wins": 1,
  "top5_losses": 2,
  "top5_voids": 2,
  "top5_staked": 37,
  "top5_profit": -11.6,
  "top5_accuracy": 33.3,
  "top5_roi_pct": -31.4
}