{
  "date": "2026-04-21",
  "settled_at": "2026-04-22T04:09:33.448996+00:00",
  "simples": [
    {
      "home_team": "Brighton & Hove Albion",
      "away_team": "Chelsea",
      "sport": "football",
      "market": "1X2",
      "pick_value": "1",
      "odds": 2.45,
      "stake": 7,
      "confidence": 7,
      "result": "win",
      "profit": 10.15,
      "final_score": "3-0"
    },
    {
      "home_team": "Racing Genk",
      "away_team": "Royal Charleroi SC",
      "sport": "football",
      "market": "btts",
      "pick_value": "btts_yes",
      "odds": 1.615,
      "stake": 8,
      "confidence": 8,
      "result": "win",
      "profit": 4.92,
      "final_score": "1-1"
    },
    {
      "home_team": "Maja Chwalinska",
      "away_team": "Miroslava Medvedeva",
      "sport": "tennis",
      "market": "1X2",
      "pick_value": "1",
      "odds": 1.001,
      "stake": 10,
      "confidence": 10,
      "result": "win",
      "profit": 0.01,
      "final_score": "1-0"
    },
    {
      "home_team": "Angelina Voloshchuk",
      "away_team": "Linda Klimovicova",
      "sport": "tennis",
      "market": "1X2",
      "pick_value": "2",
      "odds": 1.25,
      "stake": 9,
      "confidence": 9,
      "result": "win",
      "profit": 2.25,
      "final_score": "0-1"
    }
  ],
  "combos": [],
  "summary": {
    "wins": 4,
    "losses": 0,
    "total": 4,
    "profit_units": 17.33
  }
}